ros_visualization_msgs-5.5.1.data/data/include/visualization_msgs/visualization_msgs/msg/image_marker.h
ros_visualization_msgs-5.5.1.data/data/include/visualization_msgs/visualization_msgs/msg/image_marker.hpp
ros_visualization_msgs-5.5.1.data/data/include/visualization_msgs/visualization_msgs/msg/interactive_marker.h
ros_visualization_msgs-5.5.1.data/data/include/visualization_msgs/visualization_msgs/msg/interactive_marker.hpp
ros_visualization_msgs-5.5.1.data/data/include/visualization_msgs/visualization_msgs/msg/interactive_marker_control.h
ros_visualization_msgs-5.5.1.data/data/include/visualization_msgs/visualization_msgs/msg/interactive_marker_control.hpp
ros_visualization_msgs-5.5.1.data/data/include/visualization_msgs/visualization_msgs/msg/interactive_marker_feedback.h
ros_visualization_msgs-5.5.1.data/data/include/visualization_msgs/visualization_msgs/msg/interactive_marker_feedback.hpp
ros_visualization_msgs-5.5.1.data/data/include/visualization_msgs/visualization_msgs/msg/interactive_marker_init.h
ros_visualization_msgs-5.5.1.data/data/include/visualization_msgs/visualization_msgs/msg/interactive_marker_init.hpp
ros_visualization_msgs-5.5.1.data/data/include/visualization_msgs/visualization_msgs/msg/interactive_marker_pose.h
ros_visualization_msgs-5.5.1.data/data/include/visualization_msgs/visualization_msgs/msg/interactive_marker_pose.hpp
ros_visualization_msgs-5.5.1.data/data/include/visualization_msgs/visualization_msgs/msg/interactive_marker_update.h
ros_visualization_msgs-5.5.1.data/data/include/visualization_msgs/visualization_msgs/msg/interactive_marker_update.hpp
ros_visualization_msgs-5.5.1.data/data/include/visualization_msgs/visualization_msgs/msg/marker.h
ros_visualization_msgs-5.5.1.data/data/include/visualization_msgs/visualization_msgs/msg/marker.hpp
ros_visualization_msgs-5.5.1.data/data/include/visualization_msgs/visualization_msgs/msg/marker_array.h
ros_visualization_msgs-5.5.1.data/data/lib/python3.10/site-packages/visualization_msgs-5.5.1-py3.10.egg-info/PKG-INFO
ros_visualization_msgs-5.5.1.data/data/lib/python3.10/site-packages/visualization_msgs-5.5.1-py3.10.egg-info/SOURCES.txt
ros_visualization_msgs-5.5.1.data/data/lib/python3.10/site-packages/visualization_msgs-5.5.1-py3.10.egg-info/dependency_links.txt
ros_visualization_msgs-5.5.1.data/data/lib/python3.10/site-packages/visualization_msgs-5.5.1-py3.10.egg-info/top_level.txt
ros_visualization_msgs-5.5.1.dist-info/METADATA
ros_visualization_msgs-5.5.1.dist-info/WHEEL
ros_visualization_msgs-5.5.1.dist-info/top_level.txt
ros_visualization_msgs-5.5.1.dist-info/RECORD
ros_visualization_msgs-5.5.1.dist-info/licenses/LICENSE
