Metadata-Version: 2.4
Name: ros-visualization-msgs
Version: 5.5.1
Summary: ROS visualization_msgs package provides standard messages for displaying and interacting with 3D information in ROS GUI tools like RViz.
License-File: LICENSE
Requires-Dist: ros-geometry-msgs~=5.5.1
Requires-Dist: ros-builtin-interfaces~=2.3.0
Requires-Dist: ros-sensor-msgs~=5.5.1
Requires-Dist: ros-std-msgs~=5.5.1
Requires-Dist: ros-rosidl-default-runtime~=1.7.1
Dynamic: description
Dynamic: description-content-type
Dynamic: license-file
Dynamic: requires-dist
Dynamic: summary
